tiny_gemini/__init__.py
tiny_gemini/embedder.py
tiny_gemini/llm.py
tiny_gemini/register.py
tiny_gemini/types.py
tiny_gemini/utils.py
tinygent_gemini-0.1.1007.dist-info/METADATA
tinygent_gemini-0.1.1007.dist-info/WHEEL
tinygent_gemini-0.1.1007.dist-info/entry_points.txt
tinygent_gemini-0.1.1007.dist-info/RECORD
