Metadata-Version: 2.4
Name: tinygent-gemini
Version: 0.1.1007
Requires-Dist: google-genai>=1.49.0
Requires-Dist: tinygent
